README.md
setup.cfg
setup.py
kp_imc23/__init__.py
kp_imc23/compatibility.py
kp_imc23/pipeline.py
kp_imc23.egg-info/PKG-INFO
kp_imc23.egg-info/SOURCES.txt
kp_imc23.egg-info/dependency_links.txt
kp_imc23.egg-info/requires.txt
kp_imc23.egg-info/top_level.txt
kp_imc23/config/__init__.py
kp_imc23/config/paths.py
kp_imc23/external/dioad/README.md
kp_imc23/external/dioad/setup.cfg
kp_imc23/external/dioad/setup.py
kp_imc23/external/dioad/dioad/__init__.py
kp_imc23/external/dioad/dioad/infer.py
kp_imc23/external/dioad/dioad/models.py
kp_imc23/external/dioad/dioad/processing.py
kp_imc23/external/dioad/dioad/utils.py
kp_imc23/external/dioad/dioad.egg-info/PKG-INFO
kp_imc23/external/dkmv3/.gitignore
kp_imc23/external/dkmv3/LICENSE
kp_imc23/external/dkmv3/README.md
kp_imc23/external/dkmv3/setup.py
kp_imc23/external/dkmv3/data/.gitignore
kp_imc23/external/dkmv3/demo/.gitignore
kp_imc23/external/dkmv3/demo/demo_fundamental.py
kp_imc23/external/dkmv3/demo/demo_match.py
kp_imc23/external/dkmv3/dkm/__init__.py
kp_imc23/external/dkmv3/dkm.egg-info/PKG-INFO
kp_imc23/external/dkmv3/dkm/checkpointing/__init__.py
kp_imc23/external/dkmv3/dkm/checkpointing/checkpoint.py
kp_imc23/external/dkmv3/dkm/datasets/__init__.py
kp_imc23/external/dkmv3/dkm/datasets/megadepth.py
kp_imc23/external/dkmv3/dkm/datasets/scannet.py
kp_imc23/external/dkmv3/dkm/losses/__init__.py
kp_imc23/external/dkmv3/dkm/losses/depth_match_regression_loss.py
kp_imc23/external/dkmv3/dkm/models/__init__.py
kp_imc23/external/dkmv3/dkm/models/dkm.py
kp_imc23/external/dkmv3/dkm/models/encoders.py
kp_imc23/external/dkmv3/dkm/models/deprecated/build_model.py
kp_imc23/external/dkmv3/dkm/models/deprecated/corr_channels.py
kp_imc23/external/dkmv3/dkm/models/deprecated/local_corr.py
kp_imc23/external/dkmv3/dkm/models/model_zoo/DKMv3.py
kp_imc23/external/dkmv3/dkm/models/model_zoo/__init__.py
kp_imc23/external/dkmv3/dkm/train/__init__.py
kp_imc23/external/dkmv3/dkm/train/train.py
kp_imc23/external/dkmv3/dkm/utils/__init__.py
kp_imc23/external/dkmv3/dkm/utils/kde.py
kp_imc23/external/dkmv3/dkm/utils/local_correlation.py
kp_imc23/external/dkmv3/dkm/utils/transforms.py
kp_imc23/external/dkmv3/dkm/utils/utils.py
kp_imc23/external/dkmv3/scripts/download_hpatches.sh
